MANIFEST.in
setup.cfg
setup.py
fab_scripts/__init__.py
fab_scripts/fab_utils.py
fab_scripts/fabfile_heroku.py
fab_scripts/fabfile_python_lib.py
fab_scripts/fabfile_s3.py
fab_scripts/fabfile_supervisor.py
fab_scripts/fabfile_unix.py
fab_scripts/tests.py
fabric_scripts.egg-info/PKG-INFO
fabric_scripts.egg-info/SOURCES.txt
fabric_scripts.egg-info/dependency_links.txt
fabric_scripts.egg-info/entry_points.txt
fabric_scripts.egg-info/requires.txt
fabric_scripts.egg-info/top_level.txt