Metadata-Version: 1.1
Name: fabric-scripts
Version: 0.0.25
Summary: fabric-scripts
Home-page: https://github.com/paulocheque/fabric-scripts
Author: paulocheque
Author-email: paulocheque@gmail.com
License: MIT
Keywords: python django testing fixture
Platform: UNKNOWN
Classifier: Framework :: Django
Classifier: Operating System :: OS Independent
Classifier: Topic :: Software Development
Classifier: Programming Language :: Python :: 2.7
Classifier: Programming Language :: Python :: 3.3
Classifier: Programming Language :: Python :: 3.4
Classifier: Programming Language :: Python :: Implementation :: PyPy
